aioselectel_api/__init__.py
aioselectel_api/base_client.py
aioselectel_api/client.py
aioselectel_api/config.py
aioselectel_api/exceptions.py
aioselectel_api/services/__init__.py
aioselectel_api/services/object_storage.py
aioselectel_api/session.py
aioselectel_api-0.1.4.dist-info/LICENSE
aioselectel_api-0.1.4.dist-info/METADATA
aioselectel_api-0.1.4.dist-info/WHEEL
aioselectel_api-0.1.4.dist-info/RECORD
